{
  "conversations": [
    {
      "id": 1,
      "contactName": "Adriano Ferreira",
      "phone": "556499477939",
      "lastMessage": "Tchau",
      "status": "closed",
      "updatedAt": "2025-12-03T00:14:30.319Z"
    },
    {
      "id": 2,
      "contactName": "Genivaldo Peres",
      "phone": "556499989978",
      "lastMessage": "Oi",
      "status": "open",
      "updatedAt": "2025-12-03T01:06:31.196Z"
    }
  ],
  "messagesByConversation": {
    "1": [
      {
        "id": 1,
        "direction": "in",
        "text": "Oi",
        "timestamp": "2025-12-02T19:30:28.653Z"
      },
      {
        "id": 2,
        "direction": "out",
        "text": "Oi",
        "timestamp": "2025-12-02T20:37:40.706Z"
      },
      {
        "id": 3,
        "direction": "out",
        "text": "Oi",
        "timestamp": "2025-12-02T22:09:10.453Z"
      },
      {
        "id": 4,
        "direction": "in",
        "text": "Oii",
        "timestamp": "2025-12-02T22:09:23.660Z"
      },
      {
        "id": 5,
        "direction": "in",
        "text": "Tudo bem?",
        "timestamp": "2025-12-02T22:09:33.093Z"
      },
      {
        "id": 6,
        "direction": "out",
        "text": "que lindo",
        "timestamp": "2025-12-02T22:09:35.650Z"
      },
      {
        "id": 7,
        "direction": "in",
        "text": "Kkkkkk",
        "timestamp": "2025-12-02T22:09:42.347Z"
      },
      {
        "id": 8,
        "direction": "out",
        "text": "tudo ótimo",
        "timestamp": "2025-12-02T22:09:44.759Z"
      },
      {
        "id": 9,
        "direction": "in",
        "text": "Oii",
        "timestamp": "2025-12-02T22:10:01.531Z"
      },
      {
        "id": 10,
        "direction": "out",
        "text": "tchau",
        "timestamp": "2025-12-02T22:10:26.128Z"
      },
      {
        "id": 11,
        "direction": "in",
        "text": "Tchau",
        "timestamp": "2025-12-02T22:10:39.124Z"
      }
    ],
    "2": [
      {
        "id": 1,
        "direction": "in",
        "text": "Oi",
        "timestamp": "2025-12-02T20:26:19.426Z"
      },
      {
        "id": 2,
        "direction": "out",
        "text": "Oi",
        "timestamp": "2025-12-02T20:31:27.449Z"
      },
      {
        "id": 3,
        "direction": "out",
        "text": "Oi",
        "timestamp": "2025-12-02T20:37:31.163Z"
      },
      {
        "id": 4,
        "direction": "out",
        "text": "Oi",
        "timestamp": "2025-12-02T20:37:57.001Z"
      },
      {
        "id": 5,
        "direction": "out",
        "text": "oi",
        "timestamp": "2025-12-02T20:39:47.829Z"
      },
      {
        "id": 6,
        "direction": "out",
        "text": "Oi",
        "timestamp": "2025-12-02T20:43:09.010Z"
      },
      {
        "id": 7,
        "direction": "in",
        "text": "Oi",
        "timestamp": "2025-12-02T22:08:25.986Z"
      },
      {
        "id": 8,
        "direction": "out",
        "text": "oi",
        "timestamp": "2025-12-02T22:08:39.942Z"
      },
      {
        "id": 9,
        "direction": "in",
        "text": "Oi",
        "timestamp": "2025-12-02T22:08:48.849Z"
      },
      {
        "id": 10,
        "direction": "in",
        "text": "Oi",
        "timestamp": "2025-12-02T22:10:36.497Z"
      },
      {
        "id": 11,
        "direction": "out",
        "text": "Oi de novo",
        "timestamp": "2025-12-02T22:13:53.726Z"
      },
      {
        "id": 12,
        "direction": "in",
        "text": "Oi hehee",
        "timestamp": "2025-12-02T22:14:02.927Z"
      },
      {
        "id": 13,
        "direction": "in",
        "text": "Oi",
        "timestamp": "2025-12-02T22:28:06.131Z"
      },
      {
        "id": 14,
        "direction": "out",
        "text": "Oi",
        "timestamp": "2025-12-03T00:56:13.939Z"
      },
      {
        "id": 15,
        "direction": "in",
        "text": "Oi",
        "timestamp": "2025-12-03T01:06:31.196Z"
      }
    ]
  }
}